cpsms/__init__.py
cpsms/cpsms.py
cpsms-3.0.0.dist-info/LICENSE
cpsms-3.0.0.dist-info/METADATA
cpsms-3.0.0.dist-info/WHEEL
cpsms-3.0.0.dist-info/top_level.txt
cpsms-3.0.0.dist-info/RECORD
