Metadata-Version: 2.1
Name: cpsms
Version: 3.0.0
Summary: A Python wrapper around the SMS gateway from CPSMS <https://www.cpsms.dk/>.
Author-email: Mikkel Munch Mortensen <3xm@detfalskested.dk>
Project-URL: Homepage, https://git.data.coop/gorgonzo.la/cpsms
Project-URL: Issues, https://git.data.coop/gorgonzo.la/cpsms/issues
Classifier: Programming Language :: Python :: 3
Classifier: License :: OSI Approved :: MIT License
Classifier: Operating System :: OS Independent
Requires-Python: >=3.10
License-File: LICENSE
